[
    {"name":"Milk_03","title":"崙背鮮乳-1837ml","price":"155","stock":"3"},
    {"name":"Milk_08","title":"崙背鮮乳-936ml","price":"80","stock":"2"},
    {"name":"Milk_01","title":"六甲田莊鮮乳-1837ml","price":"150","stock":"0"},
    {"name":"Milk_07","title":"六甲田莊鮮乳-936ml","price":"80","stock":"0"},
    {"name":"Milk_02","title":"柳營鮮乳-1837ml","price":"150","stock":"0"},
    {"name":"Milk_06","title":"柳營鮮乳-936ml","price":"80","stock":"0"},
    {"name":"Milk_04","title":"禾香鮮乳-1837ml","price":"155","stock":"0"},
    {"name":"Milk_09","title":"禾香鮮乳-936ml","price":"80","stock":"0"},
    {"name":"Milk_05","title":"時代好農鮮乳-1837ml","price":"140","stock":"0"},
    {"name":"Milk_10","title":"鮮乳坊鮮乳-936ml","price":"100","stock":"0"},
    {"name":"Milk_11","title":"台農鮮乳-936ml","price":"80","stock":"0"},
    {"name":"Milk_12","title":"紐西蘭鮮乳-1000ml","price":"???","stock":"0"},
    {"name":"Milk_13","title":"紐牧然鮮乳-1000ml","price":"???","stock":"0"},
    {"name":"Milk_16","title":"巧克力牛乳-936ml","price":"60","stock":"0"},
    {"name":"Milk_17","title":"六甲咖啡牛乳-936ml","price":"60","stock":"0"}
   
    
    
    
 ]